{
  "grass1": [
    1,
    2
  ],
  "cliff3": [
    3,
    4
  ],
  "dust1": [
    5,
    6
  ],
  "dirt5": [
    7
  ],
  "tile2": [
    8
  ],
  "water3": [
    9
  ],
  "snow1": [
    10,
    11,
    12,
    13
  ],
  "stone2": [
    14
  ],
  "dirt4": [
    15,
    16
  ],
  "soil6": [
    17,
    18
  ],
  "stone3": [
    19
  ],
  "cliff2": [
    20,
    21
  ],
  "water2": [
    22
  ],
  "sand2": [
    23
  ],
  "water5": [
    24
  ],
  "cliff5": [
    25,
    26
  ],
  "stone4": [
    27
  ],
  "sand5": [
    28,
    29
  ],
  "soil1": [
    30
  ],
  "mud1": [
    31
  ],
  "cliff9": [
    32
  ],
  "stone8": [
    33
  ],
  "dirt3": [
    34
  ],
  "dirt2": [
    35,
    36
  ],
  "rock1": [
    37
  ],
  "sand4": [
    38
  ],
  "water8": [
    39
  ],
  "grass6": [
    40,
    41
  ],
  "cliff8": [
    42
  ],
  "lava2": [
    43
  ],
  "stone5": [
    44
  ],
  "cliff4": [
    45
  ],
  "water4": [
    46
  ],
  "snow4": [
    47
  ],
  "mud3": [
    48
  ],
  "rock2": [
    49,
    50
  ],
  "soil3": [
    51
  ],
  "stone6": [
    52
  ],
  "cliff7": [
    53,
    54,
    55
  ],
  "grass5": [
    56,
    57
  ],
  "water7": [
    58
  ],
  "dirt1": [
    59
  ],
  "lava1": [
    60
  ],
  "sand6": [
    61,
    62
  ],
  "grass4": [
    63
  ],
  "water6": [
    64
  ],
  "cliff6": [
    65
  ],
  "stone7": [
    66
  ],
  "soil2": [
    67
  ],
  "mud2": [
    68
  ],
  "dirt7": [
    69
  ],
  "snow2": [
    70,
    71
  ],
  "soil5": [
    72,
    73,
    74,
    75,
    76,
    77,
    78
  ],
  "sand1": [
    79
  ],
  "cliff11": [
    80,
    81
  ],
  "grass2": [
    82,
    83,
    84,
    85,
    86
  ],
  "snow3": [
    87,
    88,
    89,
    90,
    91
  ],
  "dust3": [
    92
  ],
  "cliff1": [
    93
  ],
  "grass3": [
    94
  ],
  "water1": [
    95
  ],
  "tile1": [
    96,
    97,
    98
  ],
  "stone1": [
    99
  ],
  "soil4": [
    100
  ],
  "dust2": [
    101,
    102
  ],
  "mud4": [
    103
  ],
  "cliff10": [
    104
  ],
  "dirt6": [
    105
  ],
  "dirt1_cliff2": {
    "s": [
      106
    ],
    "c": [
      107
    ]
  },
  "dirt1_dirt2": {
    "s": [
      108
    ],
    "c": [
      109
    ]
  },
  "dirt1_dirt4": {
    "s": [
      110,
      112,
      114
    ],
    "c": [
      111,
      113,
      115
    ]
  },
  "dirt1_grass2": {
    "s": [
      116,
      118
    ],
    "c": [
      117,
      119
    ]
  },
  "dirt1_sand2": {
    "s": [
      120,
      122
    ],
    "c": [
      121,
      123
    ]
  },
  "dirt1_sand4": {
    "s": [
      124
    ],
    "c": [
      125
    ]
  },
  "dirt1_soil1": {
    "s": [
      126
    ],
    "c": [
      127
    ]
  },
  "dirt1_soil5": {
    "s": [
      128
    ],
    "c": [
      129
    ]
  },
  "cliff2_dirt1": {
    "s": [
      130
    ],
    "c": [
      131
    ]
  },
  "cliff2_dirt2": {
    "s": [
      132,
      134,
      136
    ],
    "c": [
      133,
      135,
      137
    ]
  },
  "cliff2_grass1": {
    "s": [
      138
    ],
    "c": [
      139
    ]
  },
  "cliff2_grass2": {
    "s": [
      140,
      142
    ],
    "c": [
      141,
      143
    ]
  },
  "cliff2_grass3": {
    "s": [
      144
    ],
    "c": [
      145
    ]
  },
  "cliff2_rock2": {
    "s": [
      146,
      148
    ],
    "c": [
      147,
      149
    ]
  },
  "cliff2_sand2": {
    "s": [
      150
    ],
    "c": [
      151
    ]
  },
  "cliff2_sand4": {
    "s": [
      152,
      154,
      156,
      158
    ],
    "c": [
      153,
      155,
      157,
      159
    ]
  },
  "cliff2_soil5": {
    "s": [
      160,
      162,
      164
    ],
    "c": [
      161,
      163,
      165
    ]
  },
  "cliff2_water5": {
    "s": [
      166,
      168
    ],
    "c": [
      167,
      169
    ]
  },
  "dirt2_cliff2": {
    "s": [
      170,
      172
    ],
    "c": [
      171,
      173
    ]
  },
  "dirt2_dirt1": {
    "s": [
      174
    ],
    "c": [
      175
    ]
  },
  "dirt2_dirt4": {
    "s": [
      176
    ],
    "c": [
      177
    ]
  },
  "dirt2_dirt5": {
    "s": [
      178,
      180,
      182
    ],
    "c": [
      179,
      181,
      183
    ]
  },
  "dirt2_dust1": {
    "s": [
      184,
      186,
      188
    ],
    "c": [
      185,
      187,
      189
    ]
  },
  "dirt2_grass1": {
    "s": [
      190
    ],
    "c": [
      191
    ]
  },
  "dirt2_grass2": {
    "s": [
      192,
      194
    ],
    "c": [
      193,
      195
    ]
  },
  "dirt2_grass3": {
    "s": [
      196
    ],
    "c": [
      197
    ]
  },
  "dirt2_rock2": {
    "s": [
      198
    ],
    "c": [
      199
    ]
  },
  "dirt2_sand1": {
    "s": [
      200
    ],
    "c": [
      201
    ]
  },
  "dirt2_sand2": {
    "s": [
      202,
      204
    ],
    "c": [
      203,
      205
    ]
  },
  "dirt2_sand4": {
    "s": [
      206
    ],
    "c": [
      207
    ]
  },
  "dirt2_soil1": {
    "s": [
      208
    ],
    "c": [
      209
    ]
  },
  "dirt2_soil3": {
    "s": [
      210,
      212,
      214,
      216,
      218
    ],
    "c": [
      211,
      213,
      215,
      217,
      219
    ]
  },
  "dirt2_soil4": {
    "s": [
      220,
      222
    ],
    "c": [
      221,
      223
    ]
  },
  "dirt2_soil5": {
    "s": [
      224,
      226
    ],
    "c": [
      225,
      227
    ]
  },
  "dirt2_stone1": {
    "s": [
      228
    ],
    "c": [
      229
    ]
  },
  "dirt2_water5": {
    "s": [
      230,
      232,
      234,
      236,
      238,
      240
    ],
    "c": [
      231,
      233,
      235,
      237,
      239,
      241
    ]
  },
  "grass1_cliff2": {
    "s": [
      242
    ],
    "c": [
      243
    ]
  },
  "grass1_dirt2": {
    "s": [
      244
    ],
    "c": [
      245
    ]
  },
  "grass1_dirt5": {
    "s": [
      246
    ],
    "c": [
      247
    ]
  },
  "grass1_dirt6": {
    "s": [
      248
    ],
    "c": [
      249
    ]
  },
  "grass1_dust2": {
    "s": [
      250,
      252
    ],
    "c": [
      251,
      253
    ]
  },
  "grass1_grass2": {
    "s": [
      254
    ],
    "c": [
      255
    ]
  },
  "grass1_grass3": {
    "s": [
      256,
      258
    ],
    "c": [
      257,
      259
    ]
  },
  "grass1_sand2": {
    "s": [
      260
    ],
    "c": [
      261
    ]
  },
  "grass1_soil4": {
    "s": [
      262,
      264,
      266
    ],
    "c": [
      263,
      265,
      267
    ]
  },
  "grass2_cliff2": {
    "s": [
      268,
      270,
      272
    ],
    "c": [
      269,
      271,
      273
    ]
  },
  "grass2_dirt1": {
    "s": [
      274
    ],
    "c": [
      275
    ]
  },
  "grass2_dirt2": {
    "s": [
      276,
      278
    ],
    "c": [
      277,
      279
    ]
  },
  "grass2_dirt6": {
    "s": [
      280
    ],
    "c": [
      281
    ]
  },
  "grass2_grass1": {
    "s": [
      282
    ],
    "c": [
      283
    ]
  },
  "grass2_grass3": {
    "s": [
      284
    ],
    "c": [
      285
    ]
  },
  "grass2_sand2": {
    "s": [
      286
    ],
    "c": [
      287
    ]
  },
  "grass2_sand4": {
    "s": [
      288
    ],
    "c": [
      289
    ]
  },
  "grass2_soil3": {
    "s": [
      290,
      292
    ],
    "c": [
      291,
      293
    ]
  },
  "grass2_soil5": {
    "s": [
      294,
      296,
      298,
      300,
      302
    ],
    "c": [
      295,
      297,
      299,
      301,
      303
    ]
  },
  "grass2_stone1": {
    "s": [
      304
    ],
    "c": [
      305
    ]
  },
  "grass3_cliff2": {
    "s": [
      306
    ],
    "c": [
      307
    ]
  },
  "grass3_dirt2": {
    "s": [
      308
    ],
    "c": [
      309
    ]
  },
  "grass3_grass1": {
    "s": [
      310
    ],
    "c": [
      311
    ]
  },
  "grass3_grass2": {
    "s": [
      312
    ],
    "c": [
      313
    ]
  },
  "grass3_soil5": {
    "s": [
      314
    ],
    "c": [
      315
    ]
  },
  "rock2_cliff2": {
    "s": [
      316
    ],
    "c": [
      317
    ]
  },
  "rock2_dirt2": {
    "s": [
      318
    ],
    "c": [
      319
    ]
  },
  "sand2_cliff2": {
    "s": [
      320
    ],
    "c": [
      321
    ]
  },
  "sand2_dirt1": {
    "s": [
      322,
      324,
      326
    ],
    "c": [
      323,
      325,
      327
    ]
  },
  "sand2_dirt2": {
    "s": [
      328
    ],
    "c": [
      329
    ]
  },
  "sand2_dirt4": {
    "s": [
      330,
      332,
      334
    ],
    "c": [
      331,
      333,
      335
    ]
  },
  "sand2_dirt6": {
    "s": [
      336
    ],
    "c": [
      337
    ]
  },
  "sand2_grass1": {
    "s": [
      338
    ],
    "c": [
      339
    ]
  },
  "sand2_grass2": {
    "s": [
      340
    ],
    "c": [
      341
    ]
  },
  "sand2_sand1": {
    "s": [
      342,
      344,
      346
    ],
    "c": [
      343,
      345,
      347
    ]
  },
  "sand2_sand4": {
    "s": [
      348,
      350,
      352
    ],
    "c": [
      349,
      351,
      353
    ]
  },
  "sand2_snow3": {
    "s": [
      354,
      356
    ],
    "c": [
      355,
      357
    ]
  },
  "sand2_soil5": {
    "s": [
      358
    ],
    "c": [
      359
    ]
  },
  "sand2_soil6": {
    "s": [
      360,
      362
    ],
    "c": [
      361,
      363
    ]
  },
  "sand2_stone1": {
    "s": [
      364
    ],
    "c": [
      365
    ]
  },
  "sand4_cliff2": {
    "s": [
      366
    ],
    "c": [
      367
    ]
  },
  "sand4_dirt1": {
    "s": [
      368
    ],
    "c": [
      369
    ]
  },
  "sand4_dirt2": {
    "s": [
      370
    ],
    "c": [
      371
    ]
  },
  "sand4_dirt6": {
    "s": [
      372,
      374
    ],
    "c": [
      373,
      375
    ]
  },
  "sand4_grass2": {
    "s": [
      376
    ],
    "c": [
      377
    ]
  },
  "sand4_sand1": {
    "s": [
      378
    ],
    "c": [
      379
    ]
  },
  "sand4_sand2": {
    "s": [
      380
    ],
    "c": [
      381
    ]
  },
  "sand4_stone1": {
    "s": [
      382
    ],
    "c": [
      383
    ]
  },
  "sand4_water5": {
    "s": [
      384
    ],
    "c": [
      385
    ]
  },
  "soil5_cliff2": {
    "s": [
      386,
      388
    ],
    "c": [
      387,
      389
    ]
  },
  "soil5_dirt1": {
    "s": [
      390
    ],
    "c": [
      391
    ]
  },
  "soil5_dirt2": {
    "s": [
      392,
      394,
      396
    ],
    "c": [
      393,
      395,
      397
    ]
  },
  "soil5_grass2": {
    "s": [
      398,
      400
    ],
    "c": [
      399,
      401
    ]
  },
  "soil5_grass3": {
    "s": [
      402
    ],
    "c": [
      403
    ]
  },
  "soil5_sand2": {
    "s": [
      404
    ],
    "c": [
      405
    ]
  },
  "water5_cliff2": {
    "s": [
      406,
      408
    ],
    "c": [
      407,
      409
    ]
  },
  "water5_dirt2": {
    "s": [
      410,
      412,
      414,
      416
    ],
    "c": [
      411,
      413,
      415,
      417
    ]
  },
  "water5_dirt6": {
    "s": [
      418,
      420
    ],
    "c": [
      419,
      421
    ]
  },
  "water5_sand4": {
    "s": [
      422
    ],
    "c": [
      423
    ]
  },
  "water5_stone1": {
    "s": [
      424
    ],
    "c": [
      425
    ]
  },
  "dirt4_dirt1": {
    "s": [
      426
    ],
    "c": [
      427
    ]
  },
  "dirt4_dirt2": {
    "s": [
      428
    ],
    "c": [
      429
    ]
  },
  "dirt4_sand2": {
    "s": [
      430,
      432,
      434,
      436
    ],
    "c": [
      431,
      433,
      435,
      437
    ]
  },
  "dirt4_snow3": {
    "s": [
      438,
      440,
      442
    ],
    "c": [
      439,
      441,
      443
    ]
  },
  "dirt4_soil1": {
    "s": [
      444,
      446
    ],
    "c": [
      445,
      447
    ]
  },
  "soil1_dirt1": {
    "s": [
      448
    ],
    "c": [
      449
    ]
  },
  "soil1_dirt2": {
    "s": [
      450
    ],
    "c": [
      451
    ]
  },
  "soil1_dirt4": {
    "s": [
      452,
      454
    ],
    "c": [
      453,
      455
    ]
  },
  "soil1_snow3": {
    "s": [
      456
    ],
    "c": [
      457
    ]
  },
  "dirt5_dirt2": {
    "s": [
      458,
      460
    ],
    "c": [
      459,
      461
    ]
  },
  "dirt5_grass1": {
    "s": [
      462
    ],
    "c": [
      463
    ]
  },
  "dirt5_soil4": {
    "s": [
      464,
      466
    ],
    "c": [
      465,
      467
    ]
  },
  "dust1_dirt2": {
    "s": [
      468,
      470
    ],
    "c": [
      469,
      471
    ]
  },
  "sand1_dirt2": {
    "s": [
      472
    ],
    "c": [
      473
    ]
  },
  "sand1_sand2": {
    "s": [
      474,
      476,
      478
    ],
    "c": [
      475,
      477,
      479
    ]
  },
  "sand1_sand4": {
    "s": [
      480
    ],
    "c": [
      481
    ]
  },
  "soil3_dirt2": {
    "s": [
      482,
      484,
      486,
      488,
      490
    ],
    "c": [
      483,
      485,
      487,
      489,
      491
    ]
  },
  "soil3_grass2": {
    "s": [
      492,
      494
    ],
    "c": [
      493,
      495
    ]
  },
  "soil3_soil4": {
    "s": [
      496
    ],
    "c": [
      497
    ]
  },
  "soil4_dirt2": {
    "s": [
      498,
      500
    ],
    "c": [
      499,
      501
    ]
  },
  "soil4_dirt5": {
    "s": [
      502,
      504
    ],
    "c": [
      503,
      505
    ]
  },
  "soil4_dust2": {
    "s": [
      506,
      508,
      510,
      512
    ],
    "c": [
      507,
      509,
      511,
      513
    ]
  },
  "soil4_grass1": {
    "s": [
      514
    ],
    "c": [
      515
    ]
  },
  "soil4_soil3": {
    "s": [
      516
    ],
    "c": [
      517
    ]
  },
  "soil4_stone8": {
    "s": [
      518
    ],
    "c": [
      519
    ]
  },
  "stone1_dirt2": {
    "s": [
      520
    ],
    "c": [
      521
    ]
  },
  "stone1_grass2": {
    "s": [
      522
    ],
    "c": [
      523
    ]
  },
  "stone1_sand2": {
    "s": [
      524
    ],
    "c": [
      525
    ]
  },
  "stone1_sand4": {
    "s": [
      526
    ],
    "c": [
      527
    ]
  },
  "stone1_water5": {
    "s": [
      528
    ],
    "c": [
      529
    ]
  },
  "snow3_dirt4": {
    "s": [
      530,
      532,
      534
    ],
    "c": [
      531,
      533,
      535
    ]
  },
  "snow3_sand2": {
    "s": [
      536,
      538
    ],
    "c": [
      537,
      539
    ]
  },
  "snow3_sand5": {
    "s": [
      540,
      542
    ],
    "c": [
      541,
      543
    ]
  },
  "snow3_snow2": {
    "s": [
      544,
      546,
      548
    ],
    "c": [
      545,
      547,
      549
    ]
  },
  "snow3_soil1": {
    "s": [
      550,
      552
    ],
    "c": [
      551,
      553
    ]
  },
  "dirt6_grass1": {
    "s": [
      554
    ],
    "c": [
      555
    ]
  },
  "dirt6_grass2": {
    "s": [
      556
    ],
    "c": [
      557
    ]
  },
  "dirt6_sand2": {
    "s": [
      558
    ],
    "c": [
      559
    ]
  },
  "dirt6_sand4": {
    "s": [
      560
    ],
    "c": [
      561
    ]
  },
  "dirt6_water5": {
    "s": [
      562,
      564
    ],
    "c": [
      563,
      565
    ]
  },
  "dust2_soil4": {
    "s": [
      566
    ],
    "c": [
      567
    ]
  },
  "soil6_sand2": {
    "s": [
      568,
      570
    ],
    "c": [
      569,
      571
    ]
  },
  "snow2_snow1": {
    "s": [
      572
    ],
    "c": [
      573
    ]
  },
  "snow2_snow3": {
    "s": [
      574,
      576,
      578,
      580,
      582,
      584
    ],
    "c": [
      575,
      577,
      579,
      581,
      583,
      585
    ]
  },
  "snow1_snow2": {
    "s": [
      586
    ],
    "c": [
      587
    ]
  },
  "stone8_soil4": {
    "s": [
      588
    ],
    "c": [
      589
    ]
  },
  "cliff2_dirt1_cliff2_dirt2": [
    590
  ],
  "cliff2_dirt2_cliff2_dirt1": [
    591
  ],
  "cliff2_cliff2_dirt1_grass2": [
    592
  ],
  "cliff2_cliff2_grass2_dirt1": [
    593
  ],
  "cliff2_cliff2_dirt1_soil5": [
    594
  ],
  "cliff2_cliff2_soil5_dirt1": [
    595
  ],
  "cliff2_cliff2_dirt2_dirt1": [
    596
  ],
  "cliff2_cliff2_dirt1_dirt2": [
    597
  ],
  "cliff2_cliff2_dirt2_grass1": [
    598,
    599
  ],
  "cliff2_cliff2_grass1_dirt2": [
    600,
    601
  ],
  "cliff2_cliff2_dirt2_soil5": [
    602
  ],
  "cliff2_cliff2_soil5_dirt2": [
    603
  ],
  "cliff2_cliff2_grass1_sand2": [
    604
  ],
  "cliff2_cliff2_sand2_grass1": [
    605
  ],
  "cliff2_grass2_cliff2_dirt1": [
    606
  ],
  "cliff2_dirt1_cliff2_grass2": [
    607
  ],
  "cliff2_cliff2_grass2_dirt2": [
    608
  ],
  "cliff2_cliff2_dirt2_grass2": [
    609
  ],
  "cliff2_cliff2_grass2_soil5": [
    610,
    611
  ],
  "cliff2_cliff2_soil5_grass2": [
    612,
    613
  ],
  "cliff2_cliff2_sand2_dirt2": [
    614
  ],
  "cliff2_cliff2_dirt2_sand2": [
    615
  ],
  "cliff2_soil5_cliff2_dirt1": [
    616
  ],
  "cliff2_dirt1_cliff2_soil5": [
    617
  ],
  "cliff2_soil5_cliff2_dirt2": [
    618
  ],
  "cliff2_dirt2_cliff2_soil5": [
    619
  ],
  "cliff2_soil5_cliff2_grass2": [
    620
  ],
  "cliff2_grass2_cliff2_soil5": [
    621
  ],
  "dirt1_dirt1_cliff2_dirt2": [
    622
  ],
  "dirt1_dirt1_dirt2_cliff2": [
    623
  ],
  "dirt1_cliff2_dirt1_dirt2": [
    624
  ],
  "dirt1_dirt2_dirt1_cliff2": [
    625
  ],
  "dirt1_dirt1_cliff2_grass2": [
    626
  ],
  "dirt1_dirt1_grass2_cliff2": [
    627
  ],
  "dirt1_dirt1_cliff2_soil5": [
    628
  ],
  "dirt1_dirt1_soil5_cliff2": [
    629
  ],
  "dirt1_cliff2_dirt1_soil5": [
    630
  ],
  "dirt1_soil5_dirt1_cliff2": [
    631
  ],
  "dirt1_dirt1_dirt2_grass2": [
    632,
    633,
    634,
    635,
    636
  ],
  "dirt1_dirt1_grass2_dirt2": [
    637,
    638,
    639,
    640,
    641
  ],
  "dirt1_dirt2_dirt1_grass2": [
    642
  ],
  "dirt1_grass2_dirt1_dirt2": [
    643
  ],
  "dirt1_dirt1_dirt2_sand4": [
    644
  ],
  "dirt1_dirt1_sand4_dirt2": [
    645
  ],
  "dirt1_dirt1_dirt2_soil5": [
    646
  ],
  "dirt1_dirt1_soil5_dirt2": [
    647
  ],
  "dirt1_dirt2_dirt1_soil5": [
    648
  ],
  "dirt1_soil5_dirt1_dirt2": [
    649
  ],
  "dirt1_grass2_dirt1_cliff2": [
    650
  ],
  "dirt1_cliff2_dirt1_grass2": [
    651
  ],
  "dirt1_sand4_dirt1_dirt2": [
    652
  ],
  "dirt1_dirt2_dirt1_sand4": [
    653
  ],
  "dirt1_dirt1_sand4_grass2": [
    654
  ],
  "dirt1_dirt1_grass2_sand4": [
    655
  ],
  "dirt1_sand4_dirt1_grass2": [
    656
  ],
  "dirt1_grass2_dirt1_sand4": [
    657
  ],
  "dirt1_dirt1_soil5_grass2": [
    658
  ],
  "dirt1_dirt1_grass2_soil5": [
    659
  ],
  "dirt1_soil5_dirt1_grass2": [
    660
  ],
  "dirt1_grass2_dirt1_soil5": [
    661
  ],
  "dirt2_dirt2_cliff2_grass1": [
    662
  ],
  "dirt2_dirt2_grass1_cliff2": [
    663
  ],
  "dirt2_cliff2_dirt2_grass1": [
    664
  ],
  "dirt2_grass1_dirt2_cliff2": [
    665
  ],
  "dirt2_dirt2_cliff2_grass2": [
    666,
    667,
    668
  ],
  "dirt2_dirt2_grass2_cliff2": [
    669,
    670,
    671
  ],
  "dirt2_cliff2_dirt2_grass2": [
    672
  ],
  "dirt2_grass2_dirt2_cliff2": [
    673
  ],
  "dirt2_dirt2_cliff2_rock2": [
    674,
    675
  ],
  "dirt2_dirt2_rock2_cliff2": [
    676,
    677
  ],
  "dirt2_dirt2_cliff2_sand2": [
    678,
    679,
    680,
    681
  ],
  "dirt2_dirt2_sand2_cliff2": [
    682,
    683,
    684,
    685
  ],
  "dirt2_cliff2_dirt2_sand2": [
    686
  ],
  "dirt2_sand2_dirt2_cliff2": [
    687
  ],
  "dirt2_cliff2_dirt2_soil5": [
    688
  ],
  "dirt2_soil5_dirt2_cliff2": [
    689
  ],
  "dirt2_dirt2_dirt1_cliff2": [
    690
  ],
  "dirt2_dirt2_cliff2_dirt1": [
    691
  ],
  "dirt2_dirt1_dirt2_cliff2": [
    692
  ],
  "dirt2_cliff2_dirt2_dirt1": [
    693
  ],
  "dirt2_dirt2_dirt1_grass2": [
    694,
    695,
    696
  ],
  "dirt2_dirt2_grass2_dirt1": [
    697,
    698,
    699
  ],
  "dirt2_dirt1_dirt2_grass2": [
    700,
    701
  ],
  "dirt2_grass2_dirt2_dirt1": [
    702,
    703
  ],
  "dirt2_dirt1_dirt2_sand2": [
    704
  ],
  "dirt2_sand2_dirt2_dirt1": [
    705
  ],
  "dirt2_dirt2_dirt1_sand4": [
    706
  ],
  "dirt2_dirt2_sand4_dirt1": [
    707
  ],
  "dirt2_dirt1_dirt2_soil5": [
    708,
    709
  ],
  "dirt2_soil5_dirt2_dirt1": [
    710,
    711
  ],
  "dirt2_dirt2_dirt5_soil4": [
    712,
    713,
    714
  ],
  "dirt2_dirt2_soil4_dirt5": [
    715,
    716,
    717
  ],
  "dirt2_dirt2_grass1_grass3": [
    718
  ],
  "dirt2_dirt2_grass3_grass1": [
    719
  ],
  "dirt2_grass1_dirt2_sand2": [
    720
  ],
  "dirt2_sand2_dirt2_grass1": [
    721
  ],
  "dirt2_dirt2_grass2_sand4": [
    722
  ],
  "dirt2_dirt2_sand4_grass2": [
    723
  ],
  "dirt2_dirt2_grass2_soil5": [
    724,
    725
  ],
  "dirt2_dirt2_soil5_grass2": [
    726,
    727
  ],
  "dirt2_grass3_dirt2_cliff2": [
    728
  ],
  "dirt2_cliff2_dirt2_grass3": [
    729
  ],
  "dirt2_dirt2_grass3_grass2": [
    730,
    731
  ],
  "dirt2_dirt2_grass2_grass3": [
    732,
    733
  ],
  "dirt2_grass3_dirt2_grass2": [
    734
  ],
  "dirt2_grass2_dirt2_grass3": [
    735
  ],
  "dirt2_dirt2_grass3_soil5": [
    736
  ],
  "dirt2_dirt2_soil5_grass3": [
    737
  ],
  "dirt2_dirt2_sand2_grass2": [
    738
  ],
  "dirt2_dirt2_grass2_sand2": [
    739
  ],
  "dirt2_sand2_dirt2_grass2": [
    740
  ],
  "dirt2_grass2_dirt2_sand2": [
    741
  ],
  "dirt2_dirt2_sand2_sand1": [
    742
  ],
  "dirt2_dirt2_sand1_sand2": [
    743
  ],
  "dirt2_sand4_dirt2_dirt1": [
    744
  ],
  "dirt2_dirt1_dirt2_sand4": [
    745
  ],
  "dirt2_sand4_dirt2_grass2": [
    746
  ],
  "dirt2_grass2_dirt2_sand4": [
    747
  ],
  "dirt2_dirt2_sand4_sand2": [
    748
  ],
  "dirt2_dirt2_sand2_sand4": [
    749
  ],
  "dirt2_sand4_dirt2_sand2": [
    750
  ],
  "dirt2_sand2_dirt2_sand4": [
    751
  ],
  "dirt2_dirt2_soil3_grass2": [
    752
  ],
  "dirt2_dirt2_grass2_soil3": [
    753
  ],
  "dirt2_soil3_dirt2_grass2": [
    754,
    755
  ],
  "dirt2_grass2_dirt2_soil3": [
    756,
    757
  ],
  "dirt2_dirt2_soil5_cliff2": [
    758
  ],
  "dirt2_dirt2_cliff2_soil5": [
    759
  ],
  "dirt2_dirt2_soil5_dirt1": [
    760
  ],
  "dirt2_dirt2_dirt1_soil5": [
    761
  ],
  "dirt2_soil5_dirt2_grass2": [
    762
  ],
  "dirt2_grass2_dirt2_soil5": [
    763
  ],
  "dirt2_dirt2_stone1_grass2": [
    764
  ],
  "dirt2_dirt2_grass2_stone1": [
    765
  ],
  "dirt4_sand2_dirt4_snow3": [
    766,
    767
  ],
  "dirt4_snow3_dirt4_sand2": [
    768,
    769
  ],
  "dirt4_dirt4_snow3_sand2": [
    770
  ],
  "dirt4_dirt4_sand2_snow3": [
    771
  ],
  "dirt4_dirt4_soil1_snow3": [
    772
  ],
  "dirt4_dirt4_snow3_soil1": [
    773
  ],
  "dirt4_soil1_dirt4_snow3": [
    774,
    775
  ],
  "dirt4_snow3_dirt4_soil1": [
    776,
    777
  ],
  "dirt5_dirt5_dirt2_soil4": [
    778,
    779
  ],
  "dirt5_dirt5_soil4_dirt2": [
    780,
    781
  ],
  "dirt5_dirt5_grass1_soil4": [
    782,
    783,
    784,
    785
  ],
  "dirt5_dirt5_soil4_grass1": [
    786,
    787,
    788,
    789
  ],
  "dirt5_soil4_dirt5_grass1": [
    790,
    791
  ],
  "dirt5_grass1_dirt5_soil4": [
    792,
    793
  ],
  "grass1_grass1_dust2_soil4": [
    794
  ],
  "grass1_grass1_soil4_dust2": [
    795
  ],
  "grass1_grass2_grass1_dirt2": [
    796
  ],
  "grass1_dirt2_grass1_grass2": [
    797
  ],
  "grass1_grass1_grass2_grass3": [
    798
  ],
  "grass1_grass1_grass3_grass2": [
    799
  ],
  "grass2_grass2_cliff2_dirt1": [
    800
  ],
  "grass2_grass2_dirt1_cliff2": [
    801
  ],
  "grass2_grass2_cliff2_dirt2": [
    802
  ],
  "grass2_grass2_dirt2_cliff2": [
    803
  ],
  "grass2_cliff2_grass2_dirt2": [
    804
  ],
  "grass2_dirt2_grass2_cliff2": [
    805
  ],
  "grass2_dirt1_grass2_cliff2": [
    806
  ],
  "grass2_cliff2_grass2_dirt1": [
    807
  ],
  "grass2_grass2_dirt1_dirt2": [
    808,
    809
  ],
  "grass2_grass2_dirt2_dirt1": [
    810,
    811
  ],
  "grass2_dirt1_grass2_dirt2": [
    812
  ],
  "grass2_dirt2_grass2_dirt1": [
    813
  ],
  "grass2_grass2_dirt1_sand4": [
    814,
    815
  ],
  "grass2_grass2_sand4_dirt1": [
    816,
    817
  ],
  "grass2_dirt1_grass2_sand4": [
    818
  ],
  "grass2_sand4_grass2_dirt1": [
    819
  ],
  "grass2_grass2_dirt1_soil5": [
    820
  ],
  "grass2_grass2_soil5_dirt1": [
    821
  ],
  "grass2_grass2_dirt2_grass1": [
    822
  ],
  "grass2_grass2_grass1_dirt2": [
    823
  ],
  "grass2_grass2_dirt2_sand2": [
    824
  ],
  "grass2_grass2_sand2_dirt2": [
    825
  ],
  "grass2_grass2_dirt2_sand4": [
    826,
    827
  ],
  "grass2_grass2_sand4_dirt2": [
    828,
    829
  ],
  "grass2_grass2_dirt2_soil5": [
    830,
    831,
    832
  ],
  "grass2_grass2_soil5_dirt2": [
    833,
    834,
    835
  ],
  "grass2_grass2_grass3_dirt2": [
    836
  ],
  "grass2_grass2_dirt2_grass3": [
    837
  ],
  "grass2_grass3_grass2_dirt2": [
    838,
    839
  ],
  "grass2_dirt2_grass2_grass3": [
    840,
    841
  ],
  "grass2_grass3_grass2_soil5": [
    842,
    843
  ],
  "grass2_soil5_grass2_grass3": [
    844,
    845
  ],
  "grass2_sand2_grass2_dirt1": [
    846
  ],
  "grass2_dirt1_grass2_sand2": [
    847
  ],
  "grass2_sand2_grass2_dirt2": [
    848,
    849
  ],
  "grass2_dirt2_grass2_sand2": [
    850,
    851
  ],
  "grass2_grass2_sand2_sand4": [
    852
  ],
  "grass2_grass2_sand4_sand2": [
    853
  ],
  "grass2_sand4_grass2_dirt2": [
    854
  ],
  "grass2_dirt2_grass2_sand4": [
    855
  ],
  "grass2_sand4_grass2_sand2": [
    856
  ],
  "grass2_sand2_grass2_sand4": [
    857
  ],
  "grass2_soil5_grass2_dirt1": [
    858
  ],
  "grass2_dirt1_grass2_soil5": [
    859
  ],
  "grass2_soil5_grass2_dirt2": [
    860
  ],
  "grass2_dirt2_grass2_soil5": [
    861
  ],
  "grass3_dirt2_grass3_grass2": [
    862
  ],
  "grass3_grass2_grass3_dirt2": [
    863
  ],
  "grass3_grass3_grass2_dirt2": [
    864
  ],
  "grass3_grass3_dirt2_grass2": [
    865
  ],
  "sand1_sand1_sand2_sand4": [
    866,
    867,
    868,
    869
  ],
  "sand1_sand1_sand4_sand2": [
    870,
    871,
    872,
    873
  ],
  "sand2_sand2_dirt2_grass2": [
    874
  ],
  "sand2_sand2_grass2_dirt2": [
    875
  ],
  "sand2_dirt2_sand2_grass2": [
    876
  ],
  "sand2_grass2_sand2_dirt2": [
    877
  ],
  "sand2_sand2_dirt4_snow3": [
    878,
    879
  ],
  "sand2_sand2_snow3_dirt4": [
    880,
    881
  ],
  "sand2_sand2_grass1_dirt2": [
    882
  ],
  "sand2_sand2_dirt2_grass1": [
    883
  ],
  "sand2_sand2_sand1_sand4": [
    884
  ],
  "sand2_sand2_sand4_sand1": [
    885
  ],
  "sand2_sand1_sand2_sand4": [
    886,
    887
  ],
  "sand2_sand4_sand2_sand1": [
    888,
    889
  ],
  "sand2_sand2_sand4_dirt2": [
    890
  ],
  "sand2_sand2_dirt2_sand4": [
    891
  ],
  "sand2_sand4_sand2_dirt2": [
    892
  ],
  "sand2_dirt2_sand2_sand4": [
    893
  ],
  "sand2_sand2_sand4_grass2": [
    894
  ],
  "sand2_sand2_grass2_sand4": [
    895
  ],
  "sand2_snow3_sand2_dirt4": [
    896
  ],
  "sand2_dirt4_sand2_snow3": [
    897
  ],
  "sand4_sand4_dirt1_dirt2": [
    898
  ],
  "sand4_sand4_dirt2_dirt1": [
    899
  ],
  "sand4_dirt1_sand4_dirt2": [
    900
  ],
  "sand4_dirt2_sand4_dirt1": [
    901
  ],
  "sand4_dirt1_sand4_grass2": [
    902
  ],
  "sand4_grass2_sand4_dirt1": [
    903
  ],
  "sand4_dirt2_sand4_grass2": [
    904
  ],
  "sand4_grass2_sand4_dirt2": [
    905
  ],
  "sand4_sand4_dirt6_water5": [
    906,
    907
  ],
  "sand4_sand4_water5_dirt6": [
    908,
    909
  ],
  "sand4_sand4_grass2_dirt1": [
    910
  ],
  "sand4_sand4_dirt1_grass2": [
    911
  ],
  "sand4_sand4_grass2_dirt2": [
    912
  ],
  "sand4_sand4_dirt2_grass2": [
    913
  ],
  "sand4_sand4_sand2_dirt2": [
    914
  ],
  "sand4_sand4_dirt2_sand2": [
    915
  ],
  "sand4_sand2_sand4_dirt2": [
    916
  ],
  "sand4_dirt2_sand4_sand2": [
    917
  ],
  "sand4_sand4_sand2_grass2": [
    918
  ],
  "sand4_sand4_grass2_sand2": [
    919
  ],
  "sand4_sand2_sand4_grass2": [
    920
  ],
  "sand4_grass2_sand4_sand2": [
    921
  ],
  "snow3_sand2_snow3_dirt4": [
    922
  ],
  "snow3_dirt4_snow3_sand2": [
    923
  ],
  "snow3_snow3_soil1_dirt4": [
    924,
    925
  ],
  "snow3_snow3_dirt4_soil1": [
    926,
    927
  ],
  "soil1_soil1_snow3_dirt4": [
    928,
    929
  ],
  "soil1_soil1_dirt4_snow3": [
    930,
    931
  ],
  "soil3_grass2_soil3_dirt2": [
    932
  ],
  "soil3_dirt2_soil3_grass2": [
    933
  ],
  "soil4_soil4_dirt5_grass1": [
    934,
    935,
    936,
    937
  ],
  "soil4_soil4_grass1_dirt5": [
    938,
    939,
    940,
    941
  ],
  "soil4_dirt5_soil4_grass1": [
    942,
    943
  ],
  "soil4_grass1_soil4_dirt5": [
    944,
    945
  ],
  "soil5_soil5_cliff2_dirt1": [
    946
  ],
  "soil5_soil5_dirt1_cliff2": [
    947
  ],
  "soil5_cliff2_soil5_dirt1": [
    948
  ],
  "soil5_dirt1_soil5_cliff2": [
    949
  ],
  "soil5_cliff2_soil5_dirt2": [
    950
  ],
  "soil5_dirt2_soil5_cliff2": [
    951
  ],
  "soil5_cliff2_soil5_grass2": [
    952,
    953
  ],
  "soil5_grass2_soil5_cliff2": [
    954,
    955
  ],
  "soil5_dirt1_soil5_dirt2": [
    956
  ],
  "soil5_dirt2_soil5_dirt1": [
    957
  ],
  "soil5_soil5_dirt2_cliff2": [
    958
  ],
  "soil5_soil5_cliff2_dirt2": [
    959
  ],
  "soil5_soil5_dirt2_dirt1": [
    960
  ],
  "soil5_soil5_dirt1_dirt2": [
    961
  ],
  "soil5_soil5_grass2_cliff2": [
    962
  ],
  "soil5_soil5_cliff2_grass2": [
    963
  ],
  "soil5_soil5_grass2_dirt1": [
    964
  ],
  "soil5_soil5_dirt1_grass2": [
    965
  ],
  "soil5_grass2_soil5_dirt1": [
    966
  ],
  "soil5_dirt1_soil5_grass2": [
    967
  ],
  "soil5_soil5_grass2_dirt2": [
    968
  ],
  "soil5_soil5_dirt2_grass2": [
    969
  ],
  "soil5_grass2_soil5_dirt2": [
    970,
    971
  ],
  "soil5_dirt2_soil5_grass2": [
    972,
    973
  ],
  "water5_water5_cliff2_dirt2": [
    974,
    975
  ],
  "water5_water5_dirt2_cliff2": [
    976,
    977
  ],
  "water5_water5_dirt6_sand4": [
    978
  ],
  "water5_water5_sand4_dirt6": [
    979
  ]
}